{ "_t" : "BH.oM.Data.Library.Dataset", "BHoM_Guid" : "5403e45f-e736-4065-bf14-07ab4089c2ef", "Name" : "USBrickImportsByMass", "Fragments" : [], "Tags" : [], "CustomData" : { }, "SourceInformation" : { "_t" : "BH.oM.Data.Library.Source", "BHoM_Guid" : "4df6c24b-a603-4116-95eb-ab486ca0c611", "Name" : "6901 Brcks, Blcks, Tls A Oth Cermc Gds Slcs Earth_Port-level Imports", "Fragments" : [], "Tags" : [], "CustomData" : { }, "SourceLink" : "http://usatrade.census.gov", "Title" : "6901 Brcks, Blcks, Tls A Oth Cermc Gds Slcs Earth_Port-level Imports", "Author" : "U.S. Department of Commerce", "ItemReference" : "", "Version" : "2021", "Publisher" : "U.S. Census Bureau, Economic Indicators Division", "Schema" : "", "Language" : "English", "Location" : "Open Government Office U.S. Census Bureau , Room 8H242B 4600 Silver Hill Road Washington, DC 20233-3700", "Copyright" : "", "Contributors" : "", "Confidence" : "Medium" }, "TimeOfCreation" : { "$date" : 1665774594454 }, "Data" : [{ "_t" : "BH.oM.EmbodiedSuffering.Elements.MaterialImportSources", "BHoM_Guid" : "05d5150d-c578-4a5e-a522-bba4b4e28729", "Name" : "UnitedStatesOfAmerica", "Fragments" : [], "Tags" : [], "CustomData" : { }, "Material" : "Bricks", "ExportCountries" : ["Australia", "Austria", "Bangladesh", "Brazil", "Canada", "China", "Denmark", "Egypt", "France", "Germany", "Greece", "HongKong", "India", "Indonesia", "Ireland", "Italy", "Japan", "Macau", "Mexico", "Morocco", "Netherlands", "Pakistan", "Poland", "Portugal", "Spain", "Taiwan", "Turkey", "Ukraine", "UnitedKingdom", "UnitedStatesOfAmerica"], "ImportRatios" : [8.7502595618661363E-08, 4.7693081402437995E-07, 7.4543044528510856E-06, 4.4841330143323144E-06, 0.0, 1.8645386417645767E-05, 1.9732335326840243E-05, 0.0, 2.8639182866961106E-06, 9.2392740676664267E-06, 2.6250778685598408E-07, 5.1626531415010207E-06, 1.8647969827611651E-05, 4.0226193242978901E-06, 0.0, 2.8637766158270138E-05, 6.2701859946172201E-07, 8.7502595618661363E-08, 0.0, 3.4287683753659075E-06, 1.0972158804137327E-05, 1.2462869690257912E-06, 4.0257944184817669E-05, 0.0, 1.3857077713781916E-06, 2.1000622948478726E-06, 7.1932967104914209E-06, 4.4551321540701295E-06, 3.3117649046529548E-06, 0.99980521672207867], "ImportCountry" : "UnitedStatesOfAmerica" }], "_bhomVersion" : "6.0" }